Parameters.v
`ifndef parameters

`define parameters


`define SIZE_OF_STATES_RESP       8
`define	SIZE_OF_HEADER_VARS       8
`define SIZE_OF_HEADER_IN_BYTES   4
`define CERTIFICATE_TIMEOUT       135
`define CHALLENGE_AUTH_TIMEOUT    635
`define GET_DIGESTS_TIMEOUT       135
`define MSG_LEN_IN_BYTES          260
`define MSG_LEN                   `MSG_LEN_IN_BYTES*8

`endif //parameters

get_digests.v
/*
*	Universidad de Costa Rica
*	Escuela de Ingeniería Eléctrica
* Proyecto Eléctrico
*
*	Autor: Andrés Sánchez López - B26214
*
*	Descripción: Este archivo es para crear el mensaje de respuesta a un GET_DIGESTS
*/

module get_digests_answer
  (
    input wire clk,
    input wire Ack_in,
    output wire [(`SIZE_OF_HEADER_VARS*`SIZE_OF_HEADER_IN_BYTES)-1:0] header,
    output wire Ack_out,
    output wire [`MSG_LEN-1-(`SIZE_OF_HEADER_VARS*`SIZE_OF_HEADER_IN_BYTES):0] payload
  );

  reg [(`SIZE_OF_HEADER_VARS*`SIZE_OF_HEADER_IN_BYTES)-1:0] header_temp;
  reg [`MSG_LEN-1-((`SIZE_OF_HEADER_VARS)*`SIZE_OF_HEADER_IN_BYTES):0] payload_temp;
  reg Ack_out_temp;

  always @ (posedge clk) begin
    if (Ack_in) begin
      header_temp = {8'h01,8'h01,8'h01,8'h07};
      payload_temp = {32'h4568787,32'hAC786425,32'hF986550};
      Ack_out_temp = 1;
    end else begin
      header_temp = 0;
      payload_temp = 0;
      Ack_out_temp = 0;
    end
  end //Always

  assign header = header_temp;
  assign payload = payload_temp;
  assign Ack_out = Ack_out_temp;

endmodule // get_digests_answer

Responder.v
/*
*	Universidad de Costa Rica
*	Escuela de Ingeniería Eléctrica
* Proyecto Eléctrico
*
*	Autor: Andrés Sánchez López - B26214
*
*	Descripción: Este archivo es el authentication responder
*/

`include "Parameters.v"

module responder
  (
    input wire clk,
    input wire reset,
    input wire resp_req_in,
    input wire [`MSG_LEN-1:0] auth_msg_resp_in,
    input wire Ack_in,
    output wire resp_req_out,
    output wire [`MSG_LEN-1:0] auth_msg_resp_out
  );

  //states
  parameter IDLE = 8'b00000001, GET_DATA = 8'b00000010, GEN_ERROR = 8'b00000100;
  parameter WHICH_REQ = 8'b00001000, GET_CERTIFICATE = 8'b00010000;
  parameter CHALLENGE = 8'b00100000, GET_DIGESTS = 8'b01000000;
  parameter SEND_MSG = 8'b10000000;
  //variables
  integer current_timeout;
  reg Error_Busy,Error_Unsupported_Protocol,Error_Invalid_Request,Error_Unspecified = 0;
  reg [`SIZE_OF_HEADER_VARS-1:0] ProtocolVersion_in,MessageType_in,Param1_in,Param2_in;
  wire [(`SIZE_OF_HEADER_VARS*`SIZE_OF_HEADER_IN_BYTES)-1:0] header;
  wire [`MSG_LEN-1-((`SIZE_OF_HEADER_VARS)*`SIZE_OF_HEADER_IN_BYTES):0] payload;
  reg [`SIZE_OF_STATES_RESP-1:0] state, next_state;
  reg [`MSG_LEN-1:0] auth_msg_resp_out_temp;
  reg resp_req_out_temp, Ack_in_get_digests;
  wire Ack_out_get_digests;

  integer resp_timeout_counter = 0;


  //-------------------------Inicio del código---------------------------------

  //Para el manejo de los timeout
  always @(posedge clk) begin
    if (resp_req_out | reset) begin
      resp_timeout_counter = 0;
    end
    else if (resp_req_in) begin
      resp_timeout_counter += 1;
    end
  end

  get_digests_answer answer_to_digests
    (
      .clk(clk),
      .Ack_in(Ack_in_get_digests),
      .header(header),
      .Ack_out(Ack_out_get_digests),
      .payload(payload)
    );

 //----------------------Lógica combinacional ---------------------------------
 always @ (*)
  begin : RESPONDER_COMB
   next_state = 7'b0;
   case (state)
     IDLE: begin
           if (resp_req_in == 1'b1) begin
             next_state = GET_DATA;
           end
           else begin
             next_state = IDLE;
           end
     end //IDLE

     GET_DATA:
     begin
          ProtocolVersion_in = auth_msg_resp_in[`MSG_LEN-1:`MSG_LEN-1-(`SIZE_OF_HEADER_VARS)];
          if (ProtocolVersion_in != 1) begin
              Error_Unsupported_Protocol <= 1'b1;
          end else begin
              Error_Unsupported_Protocol <= 1'b0;
          end
          MessageType_in = auth_msg_resp_in[`MSG_LEN-1-(`SIZE_OF_HEADER_VARS)-1:`MSG_LEN-1-(2*`SIZE_OF_HEADER_VARS)];
          Param1_in = auth_msg_resp_in[`MSG_LEN-1-(2*`SIZE_OF_HEADER_VARS)-1:`MSG_LEN-1-(3*`SIZE_OF_HEADER_VARS)];
          Param2_in = auth_msg_resp_in[`MSG_LEN-1-(3*`SIZE_OF_HEADER_VARS)-1:`MSG_LEN-1-(4*`SIZE_OF_HEADER_VARS)];
          next_state = WHICH_REQ;
     end // GET_DATA

     WHICH_REQ:
     begin
        case(MessageType_in)
          129: next_state = GET_DIGESTS;
          130: next_state = GET_CERTIFICATE;
          131: next_state = CHALLENGE;

          default: Error_Invalid_Request = 1'b1;
        endcase
     end // WHICH_REQ

     GET_DIGESTS:
     begin
        if (Ack_out_get_digests) begin
          next_state = SEND_MSG;
        end else begin
          next_state = GET_DIGESTS;
        end
     end //GET_DIGESTS

     GET_CERTIFICATE: begin
        next_state = SEND_MSG;
     end

     CHALLENGE: begin
        next_state = SEND_MSG;
     end

     GEN_ERROR: begin
        next_state = SEND_MSG;
     end

     SEND_MSG:
     begin
       if (Ack_in) begin
          next_state = IDLE;
       end
       else begin
          next_state = SEND_MSG;
       end
     end

     default: next_state = IDLE;
    endcase

  end //Always-RESPONDER_COMB

//-------------------------Lógica secuencial------------------------------------

 always @ (posedge clk) begin : Resp_SEQ
   if (reset == 1'b1) begin
     state <= IDLE;
   end
   else if (Error_Busy | Error_Unsupported_Protocol | Error_Invalid_Request | Error_Unspecified) begin
     state <= GEN_ERROR;
   end
   else begin
     state <= next_state;
   end
 end // Always-Resp_SEQ

 //---------------------------Lógica de salida----------------------------------
   always @ (posedge clk) begin : Resp_OUTPUT
     if (reset == 1'b1) begin
       resp_req_out_temp <= 1'b0;
       auth_msg_resp_out_temp <= 0;
     end
     else begin
       case (state)

         IDLE: begin
           resp_req_out_temp <= 1'b0;
           auth_msg_resp_out_temp <= 0;
         end

         GET_DIGESTS: begin
            Ack_in_get_digests <= 1'b1;
         end

         SEND_MSG:
         begin
           Ack_in_get_digests <= 1'b0;
           auth_msg_resp_out_temp <= {header,payload};
           resp_req_out_temp <= 1'b1;
         end

         default: begin
           resp_req_out_temp <= 1'b0;
           auth_msg_resp_out_temp <= 0;
         end

       endcase
     end
   end //Always-Resp_OUTPUT

//-------------------------------End of always code-----------------------------

 assign auth_msg_resp_out = auth_msg_resp_out_temp;
 assign resp_req_out = resp_req_out_temp;


endmodule // responder

driver.v
/*
*	Universidad de Costa Rica
*	Escuela de Ingeniería Eléctrica
* Proyecto Eléctrico
*
*	Autor: Andrés Sánchez López - B26214
*
*	Descripción: Este archivo contiene la FSM de lógica de obtención, lectura y
* entrega de certificados y/ o información sobre estos
*/

module driver_authentication_test
  (
    input wire TX1_p,
    input wire TX1_m,
    input wire VBUS,
    input wire CC1,
    input wire D1_p,   /*no se si entrada o salida*/
    input wire D1_m,   /*no se si entrada o salida*/
    input wire SBU1,
    input wire RX2_m,
    input wire RX2_p,
    input wire RX1_p,
    input wire RX1_m,
    input wire SBU2,
    input wire CC2,
    input wire clk,
    input wire reset,
    output wire TX2_m,
    output wire TX2_p
  );

//Constants in bits
  parameter size_of_states_reg = 3;
//states
  parameter IDLE = 3'b001, STATE1 = 3'b010, STATE2 = 3'b100;
//Constants in bytes
  parameter MaxLeafCertSize = 640, MaxIntermediateCertSize = 512, MaxACDSize = 128, MaxCertChainSize = 4096;
//Internal variables
  reg [size_of_states_reg-1:0] state, next_state;
  reg TX2_m_Temp, TX2_p_Temp;

//----------------------Combinational Logic-------------------------------------
  always @ (*) begin : FSM_COMB
    next_state = 3'b000;
    case (state)
        IDLE: begin
              if (CC1 == 1'b1) begin
                next_state = STATE1;
              end
              else if (CC2 == 1'b1) begin
                next_state = STATE2;
              end
              else begin
                next_state = IDLE;
              end
        end //IDLE

        STATE1: begin
              if (CC1 == 1'b1) begin
                next_state = STATE1;
              end
              else begin
                next_state = IDLE;
              end
        end //STATE1

        STATE2: begin
              if (CC2 == 1'b1) begin
                next_state = STATE2;
              end
              else begin
                next_state = IDLE;
              end
        end //STATE2

        default: next_state = IDLE;

    endcase
  end //ALWAYS

//-------------------------sequential logic-------------------------------------
  always @ (posedge clk) begin : FSM_SEQ
    if (reset == 1'b1) begin
      state <= IDLE;
    end
    else begin
      state <= next_state;
    end
  end // Always

//---------------------------output logic---------------------------------------
  always @ (posedge clk) begin : FSM_OUTPUT
    if (reset == 1'b1) begin
      TX2_m_Temp <= 1'b0;
      TX2_p_Temp <= 1'b0;
    end
    else begin
      case (state)

        IDLE: begin
          TX2_m_Temp <= 1'b0;
          TX2_p_Temp <= 1'b0;
        end

        STATE1: begin
          TX2_m_Temp <= 1'b1;
          TX2_p_Temp <= 1'b0;
        end

        STATE2: begin
          TX2_m_Temp <= 1'b0;
          TX2_p_Temp <= 1'b1;
        end

        default: begin
          TX2_m_Temp <= 1'b0;
          TX2_p_Temp <= 1'b0;
        end

      endcase
    end
  end //Always-FSM_OUTPUT
//---------------------------End of always Code---------------------------------

assign TX2_m = TX2_m_Temp;
assign TX2_p = TX2_p_Temp;

endmodule // driver_authentication

USB_Host_model.v
/*
*	Universidad de Costa Rica
*	Escuela de Ingeniería Eléctrica
* Proyecto Eléctrico
*
*	Autor: Andrés Sánchez López - B26214
*
*	Descripción: Este archivo es el modelo del USB host, genera las señales
* que van hacia el controlador y responde a los mensajes de este
*/


`timescale 10ns/1ps

module USB_Host_model
  (
    input wire resp_req_out,
    input wire [`MSG_LEN-1:0] auth_msg_resp_out,
    output wire [`MSG_LEN-1:0] auth_msg_resp_in,
    output Ack_out_resp,
    output resp_req_in,
    output CC1,
    output CC2,
    input wire TX2_m,
    input wire TX2_p,
    output reset,
    output clk
  );

  reg clk = 0;
  always #10 clk = !clk;         //100 MHz

  reg resp_req_in = 1;
  always @(posedge clk) begin
    if (resp_req_out) begin
      resp_req_in = 0;
    end
  end //Always

  reg Ack_out_resp = 1;

  reg [`MSG_LEN-1:0] auth_msg_resp_in_temp = {8'h01,8'h09,8'h01,8'h00,2048'h5165616516161691681};
  assign auth_msg_resp_in = auth_msg_resp_in_temp;

  reg reset = 1;
  initial begin
    # 40 reset = 0;
  end

  reg CC1 = 0;
  initial begin
    # 95  CC1 = 1;
    # 200  CC1 = 0;
    # 200 $finish;
  end

  reg CC2 = 1;
  initial begin
    # 100  CC2 = 0;
    # 200  CC2 = 1;
    # 200 $finish;
  end


endmodule

tb.v
/*
*	Universidad de Costa Rica
*	Escuela de Ingeniería Eléctrica
* Proyecto Eléctrico
*
*	Autor: Andrés Sánchez López - B26214
*
*	Descripción: Este archivo es el test bench
*/


`timescale 10ns/1ps

`include "Parameters.v"

module test;

initial begin
  $dumpfile("USB_Host_model.vcd");
  $dumpvars(0,test);
end

//Pins del receptáculo del type-C
wire TX1_p,TX1_m,VBUS,CC1,D1_p,D1_m,SBU1,RX2_m,RX2_p;
wire RX1_p,RX1_m,SBU2,D2_m,D2_p,CC2,TX2_m,TX2_p,clk,reset;
wire resp_req_in,resp_req_out,Ack_out_resp;
wire [`MSG_LEN-1:0] auth_msg_resp_out, auth_msg_resp_in;


USB_Host_model HOST
  (
    .CC1(CC1),
    .CC2(CC2),
    .TX2_m(TX2_m),
    .TX2_p(TX2_p),
    .reset(reset),
    .resp_req_in(resp_req_in),
    .auth_msg_resp_in(auth_msg_resp_in),
    .auth_msg_resp_out(auth_msg_resp_out),
    .Ack_out_resp(Ack_out_resp),
    .clk(clk)
  );

  driver_authentication_test FSM_TEST
    (
      .CC1(CC1),
      .CC2(CC2),
      .TX2_m(TX2_m),
      .TX2_p(TX2_p),
      .reset(reset),
      .clk(clk)
    );

  responder resp_test
    (
      .clk(clk),
      .reset(reset),
      .resp_req_in(resp_req_in),
      .auth_msg_resp_in(auth_msg_resp_in),
      .Ack_in(Ack_out_resp),
      .resp_req_out(resp_req_out),
      .auth_msg_resp_out(auth_msg_resp_out)
    );

endmodule

USB_Host_model.vcd
$date
	Sat Sep 23 18:21:09 2017
$end
$version
	Icarus Verilog
$end
$timescale
	1ps
$end
$scope module test $end
$var wire 1 ! resp_req_out $end
$var wire 1 " resp_req_in $end
$var wire 1 # reset $end
$var wire 1 $ clk $end
$var wire 2080 % auth_msg_resp_out [2079:0] $end
$var wire 2080 & auth_msg_resp_in [2079:0] $end
$var wire 1 ' TX2_p $end
$var wire 1 ( TX2_m $end
$var wire 1 ) CC2 $end
$var wire 1 * CC1 $end
$var wire 1 + Ack_out_resp $end
$scope module FSM_TEST $end
$var wire 1 ( TX2_m $end
$var wire 1 ' TX2_p $end
$var wire 1 # reset $end
$var wire 1 $ clk $end
$var wire 1 ) CC2 $end
$var wire 1 * CC1 $end
$var reg 1 , TX2_m_Temp $end
$var reg 1 - TX2_p_Temp $end
$var reg 3 . next_state [2:0] $end
$var reg 3 / state [2:0] $end
$scope begin FSM_COMB $end
$upscope $end
$scope begin FSM_OUTPUT $end
$upscope $end
$scope begin FSM_SEQ $end
$upscope $end
$upscope $end
$scope module HOST $end
$var wire 1 ( TX2_m $end
$var wire 1 ' TX2_p $end
$var wire 2080 0 auth_msg_resp_in [2079:0] $end
$var wire 1 1 resp_req_out $end
$var wire 2080 2 auth_msg_resp_out [2079:0] $end
$var reg 1 + Ack_out_resp $end
$var reg 1 * CC1 $end
$var reg 1 ) CC2 $end
$var reg 2080 3 auth_msg_resp_in_temp [2079:0] $end
$var reg 1 $ clk $end
$var reg 1 # reset $end
$var reg 1 " resp_req_in $end
$upscope $end
$scope module resp_test $end
$var wire 1 + Ack_in $end
$var wire 2080 4 auth_msg_resp_in [2079:0] $end
$var wire 2080 5 auth_msg_resp_out [2079:0] $end
$var wire 1 $ clk $end
$var wire 1 # reset $end
$var wire 1 " resp_req_in $end
$var wire 1 ! resp_req_out $end
$var wire 2048 6 payload [2047:0] $end
$var wire 32 7 header [31:0] $end
$var wire 1 8 Ack_out_get_digests $end
$var reg 1 9 Ack_in_get_digests $end
$var reg 1 : Error_Busy $end
$var reg 1 ; Error_Invalid_Request $end
$var reg 1 < Error_Unspecified $end
$var reg 1 = Error_Unsupported_Protocol $end
$var reg 8 > MessageType_in [7:0] $end
$var reg 8 ? Param1_in [7:0] $end
$var reg 8 @ Param2_in [7:0] $end
$var reg 8 A ProtocolVersion_in [7:0] $end
$var reg 2080 B auth_msg_resp_out_temp [2079:0] $end
$var reg 8 C next_state [7:0] $end
$var reg 1 D resp_req_out_temp $end
$var reg 8 E state [7:0] $end
$var integer 32 F resp_timeout_counter [31:0] $end
$scope module answer_to_digests $end
$var wire 1 9 Ack_in $end
$var wire 1 8 Ack_out $end
$var wire 1 $ clk $end
$var wire 32 G header [31:0] $end
$var wire 2048 H payload [2047:0] $end
$var reg 1 I Ack_out_temp $end
$var reg 32 J header_temp [31:0] $end
$var reg 2048 K payload_temp [2047:0] $end
$upscope $end
$scope begin RESPONDER_COMB $end
$upscope $end
$scope begin Resp_OUTPUT $end
$upscope $end
$scope begin Resp_SEQ $end
$upscope $end
$upscope $end
$upscope $end
$enddefinitions $end
#0
$dumpvars
bx K
bx J
xI
bx H
bx G
b0 F
bx E
xD
b1 C
bx B
bx A
bx @
bx ?
bx >
x=
0<
x;
x:
x9
x8
bx 7
bx 6
bx 5
b11000000100000000000000000000000000000000000000000000000000000000000000000000000000000000000000000000000000000000000000000000000000000000000000000000000000000000000000000000000000000000000000000000000000000000000000000000000000000000000000000000000000000000000000000000000000000000000000000000000000000000000000000000000000000000000000000000000000000000000000000000000000000000000000000000000000000000000000000000000000000000000000000000000000000000000000000000000000000000000000000000000000000000000000000000000000000000000000000000000000000000000000000000000000000000000000000000000000000000000000000000000000000000000000000000000000000000000000000000000000000000000000000000000000000000000000000000000000000000000000000000000000000000000000000000000000000000000000000000000000000000000000000000000000000000000000000000000000000000000000000000000000000000000000000000000000000000000000000000000000000000000000000000000000000000000000000000000000000000000000000000000000000000000000000000000000000000000000000000000000000000000000000000000000000000000000000000000000000000000000000000000000000000000000000000000000000000000000000000000000000000000000000000000000000000000000000000000000000000000000000000000000000000000000000000000000000000000000000000000000000000000000000000000000000000000000000000000000000000000000000000000000000000000000000000000000000000000000000000000000000000000000000000000000000000000000000000000000000000000000000000000000000000000000000000000000000000000000000000000000000000000000000000000000000000000000000000000000000000000000000000000000000000000000000000000000000000000000000000000000000000000000000000000000000000000000000000000000000000000000000000000000000000000000000000000000000000000000000000000000000000000000000000000000000000000000000000000000000000000000000000000000000000000000000000000000000000000000000000000000000000000000000000000000000000000000000000000000000000000000000000000000000000000000000000000000000000000000000000000000000000000000000000000000000000000000000000000000000000000000000000000000000000100000001000001 4
b11000000100000000000000000000000000000000000000000000000000000000000000000000000000000000000000000000000000000000000000000000000000000000000000000000000000000000000000000000000000000000000000000000000000000000000000000000000000000000000000000000000000000000000000000000000000000000000000000000000000000000000000000000000000000000000000000000000000000000000000000000000000000000000000000000000000000000000000000000000000000000000000000000000000000000000000000000000000000000000000000000000000000000000000000000000000000000000000000000000000000000000000000000000000000000000000000000000000000000000000000000000000000000000000000000000000000000000000000000000000000000000000000000000000000000000000000000000000000000000000000000000000000000000000000000000000000000000000000000000000000000000000000000000000000000000000000000000000000000000000000000000000000000000000000000000000000000000000000000000000000000000000000000000000000000000000000000000000000000000000000000000000000000000000000000000000000000000000000000000000000000000000000000000000000000000000000000000000000000000000000000000000000000000000000000000000000000000000000000000000000000000000000000000000000000000000000000000000000000000000000000000000000000000000000000000000000000000000000000000000000000000000000000000000000000000000000000000000000000000000000000000000000000000000000000000000000000000000000000000000000000000000000000000000000000000000000000000000000000000000000000000000000000000000000000000000000000000000000000000000000000000000000000000000000000000000000000000000000000000000000000000000000000000000000000000000000000000000000000000000000000000000000000000000000000000000000000000000000000000000000000000000000000000000000000000000000000000000000000000000000000000000000000000000000000000000000000000000000000000000000000000000000000000000000000000000000000000000000000000000000000000000000000000000000000000000000000000000000000000000000000000000000000000000000000000000000000000000000000000000000000000000000000000000000000000000000000000000000000000000000000000000000000100000001000001 3
bx 2
z1
b11000000100000000000000000000000000000000000000000000000000000000000000000000000000000000000000000000000000000000000000000000000000000000000000000000000000000000000000000000000000000000000000000000000000000000000000000000000000000000000000000000000000000000000000000000000000000000000000000000000000000000000000000000000000000000000000000000000000000000000000000000000000000000000000000000000000000000000000000000000000000000000000000000000000000000000000000000000000000000000000000000000000000000000000000000000000000000000000000000000000000000000000000000000000000000000000000000000000000000000000000000000000000000000000000000000000000000000000000000000000000000000000000000000000000000000000000000000000000000000000000000000000000000000000000000000000000000000000000000000000000000000000000000000000000000000000000000000000000000000000000000000000000000000000000000000000000000000000000000000000000000000000000000000000000000000000000000000000000000000000000000000000000000000000000000000000000000000000000000000000000000000000000000000000000000000000000000000000000000000000000000000000000000000000000000000000000000000000000000000000000000000000000000000000000000000000000000000000000000000000000000000000000000000000000000000000000000000000000000000000000000000000000000000000000000000000000000000000000000000000000000000000000000000000000000000000000000000000000000000000000000000000000000000000000000000000000000000000000000000000000000000000000000000000000000000000000000000000000000000000000000000000000000000000000000000000000000000000000000000000000000000000000000000000000000000000000000000000000000000000000000000000000000000000000000000000000000000000000000000000000000000000000000000000000000000000000000000000000000000000000000000000000000000000000000000000000000000000000000000000000000000000000000000000000000000000000000000000000000000000000000000000000000000000000000000000000000000000000000000000000000000000000000000000000000000000000000000000000000000000000000000000000000000000000000000000000000000000000000000000000000000000000000100000001000001 0
bx /
b1 .
x-
x,
1+
0*
1)
x(
x'
b11000000100000000000000000000000000000000000000000000000000000000000000000000000000000000000000000000000000000000000000000000000000000000000000000000000000000000000000000000000000000000000000000000000000000000000000000000000000000000000000000000000000000000000000000000000000000000000000000000000000000000000000000000000000000000000000000000000000000000000000000000000000000000000000000000000000000000000000000000000000000000000000000000000000000000000000000000000000000000000000000000000000000000000000000000000000000000000000000000000000000000000000000000000000000000000000000000000000000000000000000000000000000000000000000000000000000000000000000000000000000000000000000000000000000000000000000000000000000000000000000000000000000000000000000000000000000000000000000000000000000000000000000000000000000000000000000000000000000000000000000000000000000000000000000000000000000000000000000000000000000000000000000000000000000000000000000000000000000000000000000000000000000000000000000000000000000000000000000000000000000000000000000000000000000000000000000000000000000000000000000000000000000000000000000000000000000000000000000000000000000000000000000000000000000000000000000000000000000000000000000000000000000000000000000000000000000000000000000000000000000000000000000000000000000000000000000000000000000000000000000000000000000000000000000000000000000000000000000000000000000000000000000000000000000000000000000000000000000000000000000000000000000000000000000000000000000000000000000000000000000000000000000000000000000000000000000000000000000000000000000000000000000000000000000000000000000000000000000000000000000000000000000000000000000000000000000000000000000000000000000000000000000000000000000000000000000000000000000000000000000000000000000000000000000000000000000000000000000000000000000000000000000000000000000000000000000000000000000000000000000000000000000000000000000000000000000000000000000000000000000000000000000000000000000000000000000000000000000000000000000000000000000000000000000000000000000000000000000000000000000000000000000000100000001000001 &
bx %
0$
1#
1"
x!
$end
#100000
b100 .
b0 %
b0 2
b0 5
b0 B
0!
0D
b1 E
0'
0-
0(
0,
b1 /
b10 C
08
0I
b0 6
b0 H
b0 K
b0 7
b0 G
b0 J
1$
#200000
0$
#300000
1$
#400000
0$
0#
#500000
0=
b0 @
b0 ?
b10000001 >
b1 A
b1000 C
b100 .
b10 E
b100 /
b1 F
1$
#600000
0$
#700000
b1000000 C
b1000 E
1'
1-
b10 F
1$
#800000
0$
#900000
b1000000 C
b1000000 E
b11 F
1$
#950000
b100 .
1*
#1000000
b1 .
0$
0)
#1100000
b10 .
19
b1 /
b100 F
1$
#1200000
0$
#1300000
b10 .
0'
0-
b10 /
b10000000 C
18
1I
b1000101011010000111100001111010110001111000011001000010010100001111100110000110010101010000 6
b1000101011010000111100001111010110001111000011001000010010100001111100110000110010101010000 H
b1000101011010000111100001111010110001111000011001000010010100001111100110000110010101010000 K
b1000000010000000100000111 7
b1000000010000000100000111 G
b1000000010000000100000111 J
b101 F
1$
#1400000
0$
#1500000
b1 C
b10000000 E
1(
1,
b110 F
1$
#1600000
0$
#1700000
b10 C
1!
1D
b100000100 %
b100000100 2
b100000100 5
b100000100 B
09
b1 E
b111 F
1$
#1800000
0$
#1900000
b0 %
b0 2
b0 5
b0 B
0!
0D
b10 E
b1000 C
b0 F
08
0I
b0 6
b0 H
b0 K
b0 7
b0 G
b0 J
1$
#2000000
0$
#2100000
b1000000 C
b1000 E
b1 F
1$
#2200000
0$
#2300000
b1000000 C
b1000000 E
b10 F
1$
#2400000
0$
#2500000
19
b11 F
1$
#2600000
0$
#2700000
b10000000 C
b100 F
18
1I
b1000101011010000111100001111010110001111000011001000010010100001111100110000110010101010000 6
b1000101011010000111100001111010110001111000011001000010010100001111100110000110010101010000 H
b1000101011010000111100001111010110001111000011001000010010100001111100110000110010101010000 K
b1000000010000000100000111 7
b1000000010000000100000111 G
b1000000010000000100000111 J
1$
#2800000
0$
#2900000
b1 C
b10000000 E
b101 F
1$
#2950000
b1 .
0*
#3000000
b1 .
0$
1)
#3100000
b10 C
b100 .
1!
1D
b100000100 %
b100000100 2
b100000100 5
b100000100 B
09
b1 E
b1 /
b110 F
1$
#3200000
0$
#3300000
b100 .
b0 %
b0 2
b0 5
b0 B
0!
0D
b10 E
0(
0,
b100 /
b1000 C
08
0I
b0 6
b0 H
b0 K
b0 7
b0 G
b0 J
b0 F
1$
#3400000
0$
#3500000
b1000000 C
b1000 E
1'
1-
b1 F
1$
#3600000
0$
#3700000
b1000000 C
b1000000 E
b10 F
1$
#3800000
0$
#3900000
19
b11 F
1$
#4000000
0$
#4100000
b10000000 C
18
1I
b1000101011010000111100001111010110001111000011001000010010100001111100110000110010101010000 6
b1000101011010000111100001111010110001111000011001000010010100001111100110000110010101010000 H
b1000101011010000111100001111010110001111000011001000010010100001111100110000110010101010000 K
b1000000010000000100000111 7
b1000000010000000100000111 G
b1000000010000000100000111 J
b100 F
1$
#4200000
0$
#4300000
b1 C
b10000000 E
b101 F
1$
#4400000
0$
#4500000
b10 C
1!
1D
b100000100 %
b100000100 2
b100000100 5
b100000100 B
09
b1 E
b110 F
1$
#4600000
0$
#4700000
b0 %
b0 2
b0 5
b0 B
0!
0D
b10 E
b1000 C
b0 F
08
0I
b0 6
b0 H
b0 K
b0 7
b0 G
b0 J
1$
#4800000
0$
#4900000
b1000000 C
b1000 E
b1 F
1$
