Parameters.v
`ifndef parameters

`define parameters


`define SIZE_OF_STATES_RESP       8
`define	SIZE_OF_HEADER_VARS       8
`define SIZE_OF_HEADER_IN_BYTES   4
`define CERTIFICATE_TIMEOUT       135
`define CHALLENGE_AUTH_TIMEOUT    635
`define GET_DIGESTS_TIMEOUT       135
`define MSG_LEN_IN_BYTES          260
`define MSG_LEN                   `MSG_LEN_IN_BYTES*8

`endif //parameters

challenge.v
/*
*	Universidad de Costa Rica
*	Escuela de Ingeniería Eléctrica
* Proyecto Eléctrico
*
*	Autor: Andrés Sánchez López - B26214
*
*	Descripción: Este archivo es para crear el mensaje de respuesta a un CHALLENGE
*/


module challenge_answer
  (
    input wire clk,
    input wire Enable,
    input wire [`MSG_LEN-1:0] auth_msg_resp_in,
    input wire [`SIZE_OF_HEADER_VARS-1:0] Param1, //Slot a enviar
    output wire Error_Invalid_Request,
    output wire [(`SIZE_OF_HEADER_VARS*`SIZE_OF_HEADER_IN_BYTES)-1:0] header,
    output wire Ack_out,
    output wire [`MSG_LEN-1-(`SIZE_OF_HEADER_VARS*`SIZE_OF_HEADER_IN_BYTES):0] payload
  );

  reg [(`SIZE_OF_HEADER_VARS*`SIZE_OF_HEADER_IN_BYTES)-1:0] header_temp;
  reg [`MSG_LEN-1-(`SIZE_OF_HEADER_VARS*`SIZE_OF_HEADER_IN_BYTES):0] payload_temp;
  reg Ack_out_temp;
  reg Error_Invalid_Request_temp = 0;
  reg [231:0] Payload_in;


  always @ (posedge clk) begin
    if (Enable) begin
      Payload_in = auth_msg_resp_in[255:24];
      if (Payload_in > 0) begin
        header_temp = {`PROTOCOL_VERSION,`CHALLENGE_AUTH_CMD,Param1,`CERT_CHAINS_MASK};
        payload_temp = {`PROTOCOL_VERSION,`PROTOCOL_VERSION,`CAPABILITIES,8'h00,`CHALLENGE_AUTH_HASH};
        Ack_out_temp = 1'b1;
      end else begin
        Error_Invalid_Request_temp = 1'b1;
      end
    end //If Enable
    else begin
      header_temp = 0;
      payload_temp = 0;
      Ack_out_temp = 1'b0;
    end
  end //Always


  assign header = header_temp;
  assign payload = payload_temp;
  assign Ack_out = Ack_out_temp;
  assign Error_Invalid_Request = Error_Invalid_Request_temp;

endmodule //challenge_answer

get_digests.v
/*
*	Universidad de Costa Rica
*	Escuela de Ingeniería Eléctrica
* Proyecto Eléctrico
*
*	Autor: Andrés Sánchez López - B26214
*
*	Descripción: Este archivo es para crear el mensaje de respuesta a un GET_DIGESTS
*/

module get_digests_answer
  (
    input wire clk,
    input wire Ack_in,
    output wire [(`SIZE_OF_HEADER_VARS*`SIZE_OF_HEADER_IN_BYTES)-1:0] header,
    output wire Ack_out,
    output wire [`MSG_LEN-1-(`SIZE_OF_HEADER_VARS*`SIZE_OF_HEADER_IN_BYTES):0] payload
  );

  reg [(`SIZE_OF_HEADER_VARS*`SIZE_OF_HEADER_IN_BYTES)-1:0] header_temp;
  reg [`MSG_LEN-1-((`SIZE_OF_HEADER_VARS)*`SIZE_OF_HEADER_IN_BYTES):0] payload_temp;
  reg Ack_out_temp;
  reg Param1_digests = 1'b1;

  always @ (posedge clk) begin
    if (Ack_in) begin
      header_temp = {`PROTOCOL_VERSION,`DIGESTS_ANSWER_CMD,Param1_digests,`CERT_CHAINS_MASK};
      payload_temp = {32'h4568787,32'hAC786425,32'hF986550};
      Ack_out_temp = 1;
    end else begin
      header_temp = 0;
      payload_temp = 0;
      Ack_out_temp = 0;
    end
  end //Always

  assign header = header_temp;
  assign payload = payload_temp;
  assign Ack_out = Ack_out_temp;

endmodule // get_digests_answer

Responder.v
/*
*	Universidad de Costa Rica
*	Escuela de Ingeniería Eléctrica
* Proyecto Eléctrico
*
*	Autor: Andrés Sánchez López - B26214
*
*	Descripción: Este archivo es el authentication responder
*/

`include "Parameters.v"

module responder
  (
    input wire clk,
    input wire reset,
    input wire resp_req_in,
    input wire [`MSG_LEN-1:0] auth_msg_resp_in,
    input wire Ack_in,
    output wire resp_req_out,
    output wire [`MSG_LEN-1:0] auth_msg_resp_out
  );

  //states
  parameter IDLE = 8'b00000001, GET_DATA = 8'b00000010, GEN_ERROR = 8'b00000100;
  parameter WHICH_REQ = 8'b00001000, GET_CERTIFICATE = 8'b00010000;
  parameter CHALLENGE = 8'b00100000, GET_DIGESTS = 8'b01000000;
  parameter SEND_MSG = 8'b10000000;
  //variables
  integer current_timeout;
  reg Error_Busy_temp,Error_Unsupported_Protocol_temp,Error_Invalid_Request_temp = 0;
  wire Error_Invalid_Request,Error_Unspecified,Error_Busy,Error_Unsupported_Protocol;
  wire Error_Invalid_Request_challenge;
  reg [`SIZE_OF_HEADER_VARS-1:0] ProtocolVersion_in,MessageType_in,Param1_in,Param2_in;
  wire [`SIZE_OF_HEADER_VARS-1:0] Param1;
  reg [(`SIZE_OF_HEADER_VARS*`SIZE_OF_HEADER_IN_BYTES)-1:0] header;
  wire [(`SIZE_OF_HEADER_VARS*`SIZE_OF_HEADER_IN_BYTES)-1:0] header_challenge,header_digests;
  reg [`MSG_LEN-1-((`SIZE_OF_HEADER_VARS)*`SIZE_OF_HEADER_IN_BYTES):0] payload;
  wire [`MSG_LEN-1-((`SIZE_OF_HEADER_VARS)*`SIZE_OF_HEADER_IN_BYTES):0] payload_challenge,payload_digests;
  reg [`SIZE_OF_STATES_RESP-1:0] state, next_state;
  reg [`MSG_LEN-1:0] auth_msg_resp_out_temp;
  reg resp_req_out_temp, Ack_in_get_digests;
  wire Ack_out_get_digests,challenge_enable,challenge_answer_Ack_in;
  reg challenge_enable_temp;

  integer resp_timeout_counter = 0;


  //-------------------------Inicio del código---------------------------------

  //Para el manejo de los timeout
  always @(posedge clk) begin
    if (resp_req_out | reset) begin
      resp_timeout_counter = 0;
    end
    else if (resp_req_in) begin
      resp_timeout_counter += 1;
    end
  end

  get_digests_answer answer_to_digests
    (
      .clk(clk),
      .Ack_in(Ack_in_get_digests),
      .header(header_digests),
      .Ack_out(Ack_out_get_digests),
      .payload(payload_digests)
    );

  challenge_answer answer_to_challenge
    (
      .clk(clk),
      .Enable(challenge_enable),
      .auth_msg_resp_in(auth_msg_resp_in),
      .Param1(Param1),
      .Error_Invalid_Request(Error_Invalid_Request_challenge),
      .header(header_challenge),
      .Ack_out(challenge_answer_Ack_in),
      .payload(payload_challenge)
    );

 //----------------------Lógica combinacional ---------------------------------
 always @ (*)
  begin : RESPONDER_COMB
   next_state = 7'b0;
   case (state)
     IDLE: begin
           if (resp_req_in == 1'b1) begin
             next_state = GET_DATA;
           end
           else begin
             next_state = IDLE;
           end
     end //IDLE

     GET_DATA:
     begin
          ProtocolVersion_in = auth_msg_resp_in[`MSG_LEN-1:`MSG_LEN-1-(`SIZE_OF_HEADER_VARS)];
          if (ProtocolVersion_in != 1) begin
              Error_Unsupported_Protocol_temp <= 1'b1;
          end else begin
              Error_Unsupported_Protocol_temp <= 1'b0;
          end
          MessageType_in = auth_msg_resp_in[`MSG_LEN-1-(`SIZE_OF_HEADER_VARS)-1:`MSG_LEN-1-(2*`SIZE_OF_HEADER_VARS)];
          Param1_in = auth_msg_resp_in[`MSG_LEN-1-(2*`SIZE_OF_HEADER_VARS)-1:`MSG_LEN-1-(3*`SIZE_OF_HEADER_VARS)];
          Param2_in = auth_msg_resp_in[`MSG_LEN-1-(3*`SIZE_OF_HEADER_VARS)-1:`MSG_LEN-1-(4*`SIZE_OF_HEADER_VARS)];
          next_state = WHICH_REQ;
     end // GET_DATA

     WHICH_REQ:
     begin
        case(MessageType_in)
          129: next_state = GET_DIGESTS;
          130: next_state = GET_CERTIFICATE;
          131: next_state = CHALLENGE;

          default: Error_Invalid_Request_temp = 1'b1;
        endcase
     end // WHICH_REQ

     GET_DIGESTS:
     begin
        if (Ack_out_get_digests == 1'b1) begin
          next_state = SEND_MSG;
        end else begin
          next_state = GET_DIGESTS;
        end
     end //GET_DIGESTS

     GET_CERTIFICATE:
     begin
        next_state = SEND_MSG;
     end

     CHALLENGE:
     begin
        if (challenge_answer_Ack_in == 1'b1) begin
          next_state = SEND_MSG;
        end else begin
          next_state = CHALLENGE;
        end
     end //CHALLENGE

     GEN_ERROR:
     begin
        next_state = SEND_MSG;
     end

     SEND_MSG:
     begin
       if (Ack_in) begin
          next_state = IDLE;
       end
       else begin
          next_state = SEND_MSG;
       end
     end

     default: next_state = IDLE;
    endcase

  end //Always-RESPONDER_COMB

//-------------------------Lógica secuencial------------------------------------

 always @ (posedge clk) begin : Resp_SEQ
   if (reset == 1'b1) begin
     state <= IDLE;
   end
   else if (Error_Busy_temp | Error_Unsupported_Protocol_temp | Error_Invalid_Request | Error_Unspecified | Error_Invalid_Request_challenge) begin
     state <= GEN_ERROR;
   end
   else begin
     state <= next_state;
   end
 end // Always-Resp_SEQ

 //---------------------------Lógica de salida----------------------------------
   always @ (negedge clk) begin : Resp_OUTPUT
     if (reset == 1'b1) begin
       resp_req_out_temp <= 1'b0;
       auth_msg_resp_out_temp <= 0;
     end
     else begin
       case (state)

         IDLE: begin
           resp_req_out_temp <= 1'b0;
           auth_msg_resp_out_temp <= 0;
         end

         GET_DIGESTS: begin
            payload <= payload_digests;
            header <= header_digests;
            Ack_in_get_digests <= 1'b1;
         end

         CHALLENGE:
         begin
            header <= header_challenge;
            payload <= payload_challenge;
            challenge_enable_temp = 1'b1;
         end

         SEND_MSG:
         begin
           challenge_enable_temp <= 1'b0;
           Ack_in_get_digests <= 1'b0;
           auth_msg_resp_out_temp <= {header,payload};
           resp_req_out_temp <= 1'b1;
         end

         default: begin
           resp_req_out_temp <= 1'b0;
           auth_msg_resp_out_temp <= 0;
         end

       endcase
     end
   end //Always-Resp_OUTPUT

//-------------------------------End of always code-----------------------------

 assign auth_msg_resp_out = auth_msg_resp_out_temp;
 assign resp_req_out = resp_req_out_temp;
 assign Error_Busy = Error_Busy_temp;
 assign Error_Unsupported_Protocol = Error_Unsupported_Protocol_temp;
 assign Error_Invalid_Request = Error_Invalid_Request_temp;
 assign Param1 = Param1_in;
 assign challenge_enable = challenge_enable_temp;


endmodule // responder

driver.v
/*
*	Universidad de Costa Rica
*	Escuela de Ingeniería Eléctrica
* Proyecto Eléctrico
*
*	Autor: Andrés Sánchez López - B26214
*
*	Descripción: Este archivo contiene la FSM de lógica de obtención, lectura y
* entrega de certificados y/ o información sobre estos
*/

module driver_authentication_test
  (
    input wire TX1_p,
    input wire TX1_m,
    input wire VBUS,
    input wire CC1,
    input wire D1_p,   /*no se si entrada o salida*/
    input wire D1_m,   /*no se si entrada o salida*/
    input wire SBU1,
    input wire RX2_m,
    input wire RX2_p,
    input wire RX1_p,
    input wire RX1_m,
    input wire SBU2,
    input wire CC2,
    input wire clk,
    input wire reset,
    output wire TX2_m,
    output wire TX2_p
  );

//Constants in bits
  parameter size_of_states_reg = 3;
//states
  parameter IDLE = 3'b001, STATE1 = 3'b010, STATE2 = 3'b100;
//Constants in bytes
  parameter MaxLeafCertSize = 640, MaxIntermediateCertSize = 512, MaxACDSize = 128, MaxCertChainSize = 4096;
//Internal variables
  reg [size_of_states_reg-1:0] state, next_state;
  reg TX2_m_Temp, TX2_p_Temp;

//----------------------Combinational Logic-------------------------------------
  always @ (*) begin : FSM_COMB
    next_state = 3'b000;
    case (state)
        IDLE: begin
              if (CC1 == 1'b1) begin
                next_state = STATE1;
              end
              else if (CC2 == 1'b1) begin
                next_state = STATE2;
              end
              else begin
                next_state = IDLE;
              end
        end //IDLE

        STATE1: begin
              if (CC1 == 1'b1) begin
                next_state = STATE1;
              end
              else begin
                next_state = IDLE;
              end
        end //STATE1

        STATE2: begin
              if (CC2 == 1'b1) begin
                next_state = STATE2;
              end
              else begin
                next_state = IDLE;
              end
        end //STATE2

        default: next_state = IDLE;

    endcase
  end //ALWAYS

//-------------------------sequential logic-------------------------------------
  always @ (posedge clk) begin : FSM_SEQ
    if (reset == 1'b1) begin
      state <= IDLE;
    end
    else begin
      state <= next_state;
    end
  end // Always

//---------------------------output logic---------------------------------------
  always @ (posedge clk) begin : FSM_OUTPUT
    if (reset == 1'b1) begin
      TX2_m_Temp <= 1'b0;
      TX2_p_Temp <= 1'b0;
    end
    else begin
      case (state)

        IDLE: begin
          TX2_m_Temp <= 1'b0;
          TX2_p_Temp <= 1'b0;
        end

        STATE1: begin
          TX2_m_Temp <= 1'b1;
          TX2_p_Temp <= 1'b0;
        end

        STATE2: begin
          TX2_m_Temp <= 1'b0;
          TX2_p_Temp <= 1'b1;
        end

        default: begin
          TX2_m_Temp <= 1'b0;
          TX2_p_Temp <= 1'b0;
        end

      endcase
    end
  end //Always-FSM_OUTPUT
//---------------------------End of always Code---------------------------------

assign TX2_m = TX2_m_Temp;
assign TX2_p = TX2_p_Temp;

endmodule // driver_authentication

USB_Host_model.v
/*
*	Universidad de Costa Rica
*	Escuela de Ingeniería Eléctrica
* Proyecto Eléctrico
*
*	Autor: Andrés Sánchez López - B26214
*
*	Descripción: Este archivo es el modelo del USB host, genera las señales
* que van hacia el controlador y responde a los mensajes de este
*/


`timescale 10ns/1ps

module USB_Host_model
  (
    input wire resp_req_out,
    input wire [`MSG_LEN-1:0] auth_msg_resp_out,
    output wire [`MSG_LEN-1:0] auth_msg_resp_in,
    output Ack_out_resp,
    output resp_req_in,
    output CC1,
    output CC2,
    input wire TX2_m,
    input wire TX2_p,
    output reset,
    output clk
  );

  reg clk = 0;
  always #10 clk = !clk;         //100 MHz

  reg resp_req_in = 1;
  always @(posedge clk) begin
    if (resp_req_out) begin
      resp_req_in = 0;
    end
  end //Always

  reg Ack_out_resp = 1;

  reg [`MSG_LEN-1:0] auth_msg_resp_in_temp = {8'h01,8'h09,8'h01,8'h00,2048'h5165616516161691681};
  assign auth_msg_resp_in = auth_msg_resp_in_temp;

  reg reset = 1;
  initial begin
    # 40 reset = 0;
  end

  reg CC1 = 0;
  initial begin
    # 95  CC1 = 1;
    # 200  CC1 = 0;
    # 200 $finish;
  end

  reg CC2 = 1;
  initial begin
    # 100  CC2 = 0;
    # 200  CC2 = 1;
    # 200 $finish;
  end


endmodule

tb.v
/*
*	Universidad de Costa Rica
*	Escuela de Ingeniería Eléctrica
* Proyecto Eléctrico
*
*	Autor: Andrés Sánchez López - B26214
*
*	Descripción: Este archivo es el test bench
*/


`timescale 10ns/1ps

`include "Parameters.v"

module test;

initial begin
  $dumpfile("USB_Host_model.vcd");
  $dumpvars(0,test);
end

//Pins del receptáculo del type-C
wire TX1_p,TX1_m,VBUS,CC1,D1_p,D1_m,SBU1,RX2_m,RX2_p;
wire RX1_p,RX1_m,SBU2,D2_m,D2_p,CC2,TX2_m,TX2_p,clk,reset;
wire resp_req_in,resp_req_out,Ack_out_resp;
wire [`MSG_LEN-1:0] auth_msg_resp_out, auth_msg_resp_in;


USB_Host_model HOST
  (
    .CC1(CC1),
    .CC2(CC2),
    .TX2_m(TX2_m),
    .TX2_p(TX2_p),
    .reset(reset),
    .resp_req_in(resp_req_in),
    .auth_msg_resp_in(auth_msg_resp_in),
    .auth_msg_resp_out(auth_msg_resp_out),
    .Ack_out_resp(Ack_out_resp),
    .clk(clk)
  );

  driver_authentication_test FSM_TEST
    (
      .CC1(CC1),
      .CC2(CC2),
      .TX2_m(TX2_m),
      .TX2_p(TX2_p),
      .reset(reset),
      .clk(clk)
    );

  responder resp_test
    (
      .clk(clk),
      .reset(reset),
      .resp_req_in(resp_req_in),
      .auth_msg_resp_in(auth_msg_resp_in),
      .Ack_in(Ack_out_resp),
      .resp_req_out(resp_req_out),
      .auth_msg_resp_out(auth_msg_resp_out)
    );

endmodule

USB_Host_model.vcd
$date
	Mon Sep 25 21:59:36 2017
$end
$version
	Icarus Verilog
$end
$timescale
	1ps
$end
$scope module test $end
$var wire 1 ! resp_req_out $end
$var wire 1 " resp_req_in $end
$var wire 1 # reset $end
$var wire 1 $ clk $end
$var wire 2080 % auth_msg_resp_out [2079:0] $end
$var wire 2080 & auth_msg_resp_in [2079:0] $end
$var wire 1 ' TX2_p $end
$var wire 1 ( TX2_m $end
$var wire 1 ) CC2 $end
$var wire 1 * CC1 $end
$var wire 1 + Ack_out_resp $end
$scope module FSM_TEST $end
$var wire 1 ( TX2_m $end
$var wire 1 ' TX2_p $end
$var wire 1 # reset $end
$var wire 1 $ clk $end
$var wire 1 ) CC2 $end
$var wire 1 * CC1 $end
$var reg 1 , TX2_m_Temp $end
$var reg 1 - TX2_p_Temp $end
$var reg 3 . next_state [2:0] $end
$var reg 3 / state [2:0] $end
$scope begin FSM_COMB $end
$upscope $end
$scope begin FSM_OUTPUT $end
$upscope $end
$scope begin FSM_SEQ $end
$upscope $end
$upscope $end
$scope module HOST $end
$var wire 1 ( TX2_m $end
$var wire 1 ' TX2_p $end
$var wire 2080 0 auth_msg_resp_in [2079:0] $end
$var wire 1 1 resp_req_out $end
$var wire 2080 2 auth_msg_resp_out [2079:0] $end
$var reg 1 + Ack_out_resp $end
$var reg 1 * CC1 $end
$var reg 1 ) CC2 $end
$var reg 2080 3 auth_msg_resp_in_temp [2079:0] $end
$var reg 1 $ clk $end
$var reg 1 # reset $end
$var reg 1 " resp_req_in $end
$upscope $end
$scope module resp_test $end
$var wire 1 + Ack_in $end
$var wire 1 4 Error_Busy $end
$var wire 1 5 Error_Invalid_Request $end
$var wire 1 6 Error_Unspecified $end
$var wire 1 7 Error_Unsupported_Protocol $end
$var wire 8 8 Param1 [7:0] $end
$var wire 2080 9 auth_msg_resp_in [2079:0] $end
$var wire 2080 : auth_msg_resp_out [2079:0] $end
$var wire 1 ; challenge_enable $end
$var wire 1 $ clk $end
$var wire 1 # reset $end
$var wire 1 " resp_req_in $end
$var wire 1 ! resp_req_out $end
$var wire 2048 < payload_digests [2047:0] $end
$var wire 2048 = payload_challenge [2047:0] $end
$var wire 32 > header_digests [31:0] $end
$var wire 32 ? header_challenge [31:0] $end
$var wire 1 @ challenge_answer_Ack_in $end
$var wire 1 A Error_Invalid_Request_challenge $end
$var wire 1 B Ack_out_get_digests $end
$var reg 1 C Ack_in_get_digests $end
$var reg 1 D Error_Busy_temp $end
$var reg 1 E Error_Invalid_Request_temp $end
$var reg 1 F Error_Unsupported_Protocol_temp $end
$var reg 8 G MessageType_in [7:0] $end
$var reg 8 H Param1_in [7:0] $end
$var reg 8 I Param2_in [7:0] $end
$var reg 8 J ProtocolVersion_in [7:0] $end
$var reg 2080 K auth_msg_resp_out_temp [2079:0] $end
$var reg 1 L challenge_enable_temp $end
$var reg 32 M header [31:0] $end
$var reg 8 N next_state [7:0] $end
$var reg 2048 O payload [2047:0] $end
$var reg 1 P resp_req_out_temp $end
$var reg 8 Q state [7:0] $end
$var integer 32 R resp_timeout_counter [31:0] $end
$scope module answer_to_challenge $end
$var wire 1 @ Ack_out $end
$var wire 1 ; Enable $end
$var wire 1 A Error_Invalid_Request $end
$var wire 8 S Param1 [7:0] $end
$var wire 2080 T auth_msg_resp_in [2079:0] $end
$var wire 1 $ clk $end
$var wire 32 U header [31:0] $end
$var wire 2048 V payload [2047:0] $end
$var reg 1 W Ack_out_temp $end
$var reg 1 X Error_Invalid_Request_temp $end
$var reg 232 Y Payload_in [231:0] $end
$var reg 32 Z header_temp [31:0] $end
$var reg 2048 [ payload_temp [2047:0] $end
$upscope $end
$scope module answer_to_digests $end
$var wire 1 C Ack_in $end
$var wire 1 B Ack_out $end
$var wire 1 $ clk $end
$var wire 32 \ header [31:0] $end
$var wire 2048 ] payload [2047:0] $end
$var reg 1 ^ Ack_out_temp $end
$var reg 1 _ Param1_digests $end
$var reg 32 ` header_temp [31:0] $end
$var reg 2048 a payload_temp [2047:0] $end
$upscope $end
$scope begin RESPONDER_COMB $end
$upscope $end
$scope begin Resp_OUTPUT $end
$upscope $end
$scope begin Resp_SEQ $end
$upscope $end
$upscope $end
$upscope $end
$enddefinitions $end
#0
$dumpvars
bx a
bx `
1_
x^
bx ]
bx \
bx [
bx Z
bx Y
xX
xW
bx V
bx U
b11000001100000001000000000000000000000000000000000000000000000000000000000000000000000000000000000000000000000000000000000000000000000000000000000000000000000000000000000000000000000000000000000000000000000000000000000000000000000000000000000000000000000000000000000000000000000000000000000000000000000000000000000000000000000000000000000000000000000000000000000000000000000000000000000000000000000000000000000000000000000000000000000000000000000000000000000000000000000000000000000000000000000000000000000000000000000000000000000000000000000000000000000000000000000000000000000000000000000000000000000000000000000000000000000000000000000000000000000000000000000000000000000000000000000000000000000000000000000000000000000000000000000000000000000000000000000000000000000000000000000000000000000000000000000000000000000000000000000000000000000000000000000000000000000000000000000000000000000000000000000000000000000000000000000000000000000000000000000000000000000000000000000000000000000000000000000000000000000000000000000000000000000000000000000000000000000000000000000000000000000000000000000000000000000000000000000000000000000000000000000000000000000000000000000000000000000000000000000000000000000000000000000000000000000000000000000000000000000000000000000000000000000000000000000000000000000000000000000000000000000000000000000000000000000000000000000000000000000000000000000000000000000000000000000000000000000000000000000000000000000000000000000000000000000000000000000000000000000000000000000000000000000000000000000000000000000000000000000000000000000000000000000000000000000000000000000000000000000000000000000000000000000000000000000000000000000000000000000000000000000000000000000000000000000000000000000000000000000000000000000000000000000000000000000000000000000000000000000000000000000000000000000000000000000000000000000000000000000000000000000000000000000000000000000000000000000000000000000000000000000000000000000000000000000000000000000000000000000000000000000000000000000000101000101100101011000010110010100010110000101100001011010010001011010000001 T
bx S
b0 R
bx Q
xP
bx O
b1 N
bx M
xL
bx K
bx J
bx I
bx H
bx G
xF
0E
xD
xC
xB
xA
x@
bx ?
bx >
bx =
bx <
x;
bx :
b11000001100000001000000000000000000000000000000000000000000000000000000000000000000000000000000000000000000000000000000000000000000000000000000000000000000000000000000000000000000000000000000000000000000000000000000000000000000000000000000000000000000000000000000000000000000000000000000000000000000000000000000000000000000000000000000000000000000000000000000000000000000000000000000000000000000000000000000000000000000000000000000000000000000000000000000000000000000000000000000000000000000000000000000000000000000000000000000000000000000000000000000000000000000000000000000000000000000000000000000000000000000000000000000000000000000000000000000000000000000000000000000000000000000000000000000000000000000000000000000000000000000000000000000000000000000000000000000000000000000000000000000000000000000000000000000000000000000000000000000000000000000000000000000000000000000000000000000000000000000000000000000000000000000000000000000000000000000000000000000000000000000000000000000000000000000000000000000000000000000000000000000000000000000000000000000000000000000000000000000000000000000000000000000000000000000000000000000000000000000000000000000000000000000000000000000000000000000000000000000000000000000000000000000000000000000000000000000000000000000000000000000000000000000000000000000000000000000000000000000000000000000000000000000000000000000000000000000000000000000000000000000000000000000000000000000000000000000000000000000000000000000000000000000000000000000000000000000000000000000000000000000000000000000000000000000000000000000000000000000000000000000000000000000000000000000000000000000000000000000000000000000000000000000000000000000000000000000000000000000000000000000000000000000000000000000000000000000000000000000000000000000000000000000000000000000000000000000000000000000000000000000000000000000000000000000000000000000000000000000000000000000000000000000000000000000000000000000000000000000000000000000000000000000000000000000000000000000000000000000000000000000000000101000101100101011000010110010100010110000101100001011010010001011010000001 9
bx 8
x7
z6
05
x4
b11000001100000001000000000000000000000000000000000000000000000000000000000000000000000000000000000000000000000000000000000000000000000000000000000000000000000000000000000000000000000000000000000000000000000000000000000000000000000000000000000000000000000000000000000000000000000000000000000000000000000000000000000000000000000000000000000000000000000000000000000000000000000000000000000000000000000000000000000000000000000000000000000000000000000000000000000000000000000000000000000000000000000000000000000000000000000000000000000000000000000000000000000000000000000000000000000000000000000000000000000000000000000000000000000000000000000000000000000000000000000000000000000000000000000000000000000000000000000000000000000000000000000000000000000000000000000000000000000000000000000000000000000000000000000000000000000000000000000000000000000000000000000000000000000000000000000000000000000000000000000000000000000000000000000000000000000000000000000000000000000000000000000000000000000000000000000000000000000000000000000000000000000000000000000000000000000000000000000000000000000000000000000000000000000000000000000000000000000000000000000000000000000000000000000000000000000000000000000000000000000000000000000000000000000000000000000000000000000000000000000000000000000000000000000000000000000000000000000000000000000000000000000000000000000000000000000000000000000000000000000000000000000000000000000000000000000000000000000000000000000000000000000000000000000000000000000000000000000000000000000000000000000000000000000000000000000000000000000000000000000000000000000000000000000000000000000000000000000000000000000000000000000000000000000000000000000000000000000000000000000000000000000000000000000000000000000000000000000000000000000000000000000000000000000000000000000000000000000000000000000000000000000000000000000000000000000000000000000000000000000000000000000000000000000000000000000000000000000000000000000000000000000000000000000000000000000000000000000000000000000000000000000000101000101100101011000010110010100010110000101100001011010010001011010000001 3
bx 2
z1
b11000001100000001000000000000000000000000000000000000000000000000000000000000000000000000000000000000000000000000000000000000000000000000000000000000000000000000000000000000000000000000000000000000000000000000000000000000000000000000000000000000000000000000000000000000000000000000000000000000000000000000000000000000000000000000000000000000000000000000000000000000000000000000000000000000000000000000000000000000000000000000000000000000000000000000000000000000000000000000000000000000000000000000000000000000000000000000000000000000000000000000000000000000000000000000000000000000000000000000000000000000000000000000000000000000000000000000000000000000000000000000000000000000000000000000000000000000000000000000000000000000000000000000000000000000000000000000000000000000000000000000000000000000000000000000000000000000000000000000000000000000000000000000000000000000000000000000000000000000000000000000000000000000000000000000000000000000000000000000000000000000000000000000000000000000000000000000000000000000000000000000000000000000000000000000000000000000000000000000000000000000000000000000000000000000000000000000000000000000000000000000000000000000000000000000000000000000000000000000000000000000000000000000000000000000000000000000000000000000000000000000000000000000000000000000000000000000000000000000000000000000000000000000000000000000000000000000000000000000000000000000000000000000000000000000000000000000000000000000000000000000000000000000000000000000000000000000000000000000000000000000000000000000000000000000000000000000000000000000000000000000000000000000000000000000000000000000000000000000000000000000000000000000000000000000000000000000000000000000000000000000000000000000000000000000000000000000000000000000000000000000000000000000000000000000000000000000000000000000000000000000000000000000000000000000000000000000000000000000000000000000000000000000000000000000000000000000000000000000000000000000000000000000000000000000000000000000000000000000000000000000000000000000101000101100101011000010110010100010110000101100001011010010001011010000001 0
bx /
b1 .
x-
x,
1+
0*
1)
x(
x'
b11000001100000001000000000000000000000000000000000000000000000000000000000000000000000000000000000000000000000000000000000000000000000000000000000000000000000000000000000000000000000000000000000000000000000000000000000000000000000000000000000000000000000000000000000000000000000000000000000000000000000000000000000000000000000000000000000000000000000000000000000000000000000000000000000000000000000000000000000000000000000000000000000000000000000000000000000000000000000000000000000000000000000000000000000000000000000000000000000000000000000000000000000000000000000000000000000000000000000000000000000000000000000000000000000000000000000000000000000000000000000000000000000000000000000000000000000000000000000000000000000000000000000000000000000000000000000000000000000000000000000000000000000000000000000000000000000000000000000000000000000000000000000000000000000000000000000000000000000000000000000000000000000000000000000000000000000000000000000000000000000000000000000000000000000000000000000000000000000000000000000000000000000000000000000000000000000000000000000000000000000000000000000000000000000000000000000000000000000000000000000000000000000000000000000000000000000000000000000000000000000000000000000000000000000000000000000000000000000000000000000000000000000000000000000000000000000000000000000000000000000000000000000000000000000000000000000000000000000000000000000000000000000000000000000000000000000000000000000000000000000000000000000000000000000000000000000000000000000000000000000000000000000000000000000000000000000000000000000000000000000000000000000000000000000000000000000000000000000000000000000000000000000000000000000000000000000000000000000000000000000000000000000000000000000000000000000000000000000000000000000000000000000000000000000000000000000000000000000000000000000000000000000000000000000000000000000000000000000000000000000000000000000000000000000000000000000000000000000000000000000000000000000000000000000000000000000000000000000000000000000000000000000000101000101100101011000010110010100010110000101100001011010010001011010000001 &
bx %
0$
1#
1"
x!
$end
#100000
b100 .
b1 Q
0'
0-
0(
0,
b1 /
b10 N
0B
0^
b0 <
b0 ]
b0 a
b0 >
b0 \
b0 `
0@
0W
b0 =
b0 V
b0 [
b0 ?
b0 U
b0 Z
1$
#200000
b0 %
b0 2
b0 :
b0 K
0!
0P
0$
#300000
1$
#400000
0$
0#
#500000
07
0F
b0 I
b1 8
b1 S
b1 H
b10000011 G
b1 J
b1000 N
b100 .
b10 Q
b100 /
b1 R
1$
#600000
0$
#700000
b100000 N
b1000 Q
1'
1-
b10 R
1$
#800000
0$
#900000
b100000 N
b100000 Q
b11 R
1$
#950000
b100 .
1*
#1000000
b0 O
b0 M
1;
1L
b1 .
0$
0)
