driver.v
/*
*	Universidad de Costa Rica
*	Escuela de Ingeniería Eléctrica
* Proyecto Eléctrico
*
*	Autor: Andrés Sánchez López - B26214
*
*	Descripción: Este archivo contiene la FSM de lógica de obtención, lectura y
* entrega de certificados y/ o información sobre estos
*/

module driver_authentication_test
  (
    input wire TX1_p,
    input wire TX1_m,
    input wire VBUS,
    input wire CC1,
    input wire D1_p,   /*no se si entrada o salida*/
    input wire D1_m,   /*no se si entrada o salida*/
    input wire SBU1,
    input wire RX2_m,
    input wire RX2_p,
    input wire RX1_p,
    input wire RX1_m,
    input wire SBU2,
    input wire CC2,
    input wire clk,
    input wire reset,
    output wire TX2_m,
    output wire TX2_p
  );

//Constants in bits
  parameter size_of_states_reg = 3;
//states
  parameter IDLE = 3'b001, STATE1 = 3'b010, STATE2 = 3'b100;
//Constants in bytes
  parameter MaxLeafCertSize = 640, MaxIntermediateCertSize = 512, MaxACDSize = 128, MaxCertChainSize = 4096;
//Internal variables
  reg [size_of_states_reg-1:0] state, next_state;
  reg TX2_m_Temp, TX2_p_Temp;

//----------------------Combinational Logic-------------------------------------
  always @ (*) begin : FSM_COMB
    next_state = 3'b000;
    case (state)
        IDLE: begin
              if (CC1 == 1'b1) begin
                next_state = STATE1;
              end
              else if (CC2 == 1'b1) begin
                next_state = STATE2;
              end
              else begin
                next_state = IDLE;
              end
        end //IDLE

        STATE1: begin
              if (CC1 == 1'b1) begin
                next_state = STATE1;
              end
              else begin
                next_state = IDLE;
              end
        end //STATE1

        STATE2: begin
              if (CC2 == 1'b1) begin
                next_state = STATE2;
              end
              else begin
                next_state = IDLE;
              end
        end //STATE2

        default: next_state = IDLE;

    endcase
  end //ALWAYS

//-------------------------sequential logic-------------------------------------
  always @ (posedge clk) begin : FSM_SEQ
    if (reset == 1'b1) begin
      state <= IDLE;
    end
    else begin
      state <= next_state;
    end
  end // Always

//---------------------------output logic---------------------------------------
  always @ (posedge clk) begin : FSM_OUTPUT
    if (reset == 1'b1) begin
      TX2_m_Temp <= 1'b0;
      TX2_p_Temp <= 1'b0;
    end
    else begin
      case (state)

        IDLE: begin
          TX2_m_Temp <= 1'b0;
          TX2_p_Temp <= 1'b0;
        end

        STATE1: begin
          TX2_m_Temp <= 1'b1;
          TX2_p_Temp <= 1'b0;
        end

        STATE2: begin
          TX2_m_Temp <= 1'b0;
          TX2_p_Temp <= 1'b1;
        end

        default: begin
          TX2_m_Temp <= 1'b0;
          TX2_p_Temp <= 1'b0;
        end

      endcase
    end
  end //Always-FSM_OUTPUT
//---------------------------End of always Code---------------------------------

assign TX2_m = TX2_m_Temp;
assign TX2_p = TX2_p_Temp;

endmodule // driver_authentication

USB_Host_model.v
/*
*	Universidad de Costa Rica
*	Escuela de Ingeniería Eléctrica
* Proyecto Eléctrico
*
*	Autor: Andrés Sánchez López - B26214
*
*	Descripción: Este archivo es el modelo del USB host, genera las señales
* que van hacia el controlador y responde a los mensajes de este
*/


`timescale 10ns/1ps

module USB_Host_model
  (
    input wire TX1_p,
    input wire TX1_m,
    output reg VBUS,
    output CC1,
    output D1_p,   /*no se si entrada o salida*/
    output D1_m,   /*no se si entrada o salida*/
    output SBU1,
    output RX2_m,
    output RX2_p,
    output RX1_p,
    output RX1_m,
    output SBU2,
    output CC2,
    input wire TX2_m,
    input wire TX2_p,
    output reset,
    output clk
  );

  reg clk = 0;
  always #10 clk = !clk;         //100 MHz

  reg reset = 1;
  initial begin
    # 2 reset = 0;
  end

  reg CC1 = 0;
  initial begin
    # 95  CC1 = 1;
    # 200  CC1 = 0;
    # 50 $finish;
  end

  reg CC2 = 1;
  initial begin
    # 100  CC2 = 0;
    # 200  CC2 = 1;
    # 50 $finish;
  end


endmodule

tb.v
/*
*	Universidad de Costa Rica
*	Escuela de Ingeniería Eléctrica
* Proyecto Eléctrico
*
*	Autor: Andrés Sánchez López - B26214
*
*	Descripción: Este archivo es el test bench
*/


`timescale 10ns/1ps

module test;

initial begin
  $dumpfile("USB_Host_model.vcd");
  $dumpvars(0,test);
end

//Pins del receptáculo del type-C
wire TX1_p,TX1_m,VBUS,CC1,D1_p,D1_m,SBU1,RX2_m,RX2_p;
wire RX1_p,RX1_m,SBU2,D2_m,D2_p,CC2,TX2_m,TX2_p,clk,reset;


USB_Host_model HOST
  (
    .TX1_p(TX1_p),
    .TX1_m(TX1_m),
    .VBUS(VBUS),
    .CC1(CC1),
    .D1_p(D1_p),
    .D1_m(D1_m),
    .SBU1(SBU1),
    .RX2_m(RX2_m),
    .RX2_p(RX2_p),
    .RX1_p(RX1_p),
    .RX1_m(RX1_m),
    .SBU2(SBU2),
    .CC2(CC2),
    .TX2_m(TX2_m),
    .TX2_p(TX2_p),
    .reset(reset),
    .clk(clk)
  );

  driver_authentication_test FSM_TEST
    (
      .TX1_p(TX1_p),
      .TX1_m(TX1_m),
      .VBUS(VBUS),
      .CC1(CC1),
      .D1_p(D1_p),
      .D1_m(D1_m),
      .SBU1(SBU1),
      .RX2_m(RX2_m),
      .RX2_p(RX2_p),
      .RX1_p(RX1_p),
      .RX1_m(RX1_m),
      .SBU2(SBU2),
      .CC2(CC2),
      .TX2_m(TX2_m),
      .TX2_p(TX2_p),
      .reset(reset),
      .clk(clk)
    );

endmodule

USB_Host_model.vcd
$date
	Fri Sep  8 20:52:53 2017
$end
$version
	Icarus Verilog
$end
$timescale
	1ps
$end
$scope module test $end
$var wire 1 ! D1_m $end
$var wire 1 " D1_p $end
$var wire 1 # RX1_m $end
$var wire 1 $ RX1_p $end
$var wire 1 % RX2_m $end
$var wire 1 & RX2_p $end
$var wire 1 ' SBU1 $end
$var wire 1 ( SBU2 $end
$var wire 1 ) TX1_m $end
$var wire 1 * TX1_p $end
$var wire 1 + reset $end
$var wire 1 , clk $end
$var wire 1 - VBUS $end
$var wire 1 . TX2_p $end
$var wire 1 / TX2_m $end
$var wire 1 0 CC2 $end
$var wire 1 1 CC1 $end
$scope module FSM_TEST $end
$var wire 1 ! D1_m $end
$var wire 1 " D1_p $end
$var wire 1 # RX1_m $end
$var wire 1 $ RX1_p $end
$var wire 1 % RX2_m $end
$var wire 1 & RX2_p $end
$var wire 1 ' SBU1 $end
$var wire 1 ( SBU2 $end
$var wire 1 ) TX1_m $end
$var wire 1 * TX1_p $end
$var wire 1 / TX2_m $end
$var wire 1 . TX2_p $end
$var wire 1 + reset $end
$var wire 1 , clk $end
$var wire 1 - VBUS $end
$var wire 1 0 CC2 $end
$var wire 1 1 CC1 $end
$var reg 1 2 TX2_m_Temp $end
$var reg 1 3 TX2_p_Temp $end
$var reg 3 4 next_state [2:0] $end
$var reg 3 5 state [2:0] $end
$scope begin FSM_COMB $end
$upscope $end
$scope begin FSM_OUTPUT $end
$upscope $end
$scope begin FSM_SEQ $end
$upscope $end
$upscope $end
$scope module HOST $end
$var wire 1 ! D1_m $end
$var wire 1 " D1_p $end
$var wire 1 # RX1_m $end
$var wire 1 $ RX1_p $end
$var wire 1 % RX2_m $end
$var wire 1 & RX2_p $end
$var wire 1 ' SBU1 $end
$var wire 1 ( SBU2 $end
$var wire 1 ) TX1_m $end
$var wire 1 * TX1_p $end
$var wire 1 / TX2_m $end
$var wire 1 . TX2_p $end
$var reg 1 1 CC1 $end
$var reg 1 0 CC2 $end
$var reg 1 - VBUS $end
$var reg 1 , clk $end
$var reg 1 + reset $end
$upscope $end
$upscope $end
$enddefinitions $end
#0
$dumpvars
bx 5
b1 4
x3
x2
01
10
x/
x.
x-
0,
1+
z*
z)
z(
z'
z&
z%
z$
z#
z"
z!
$end
#20000
0+
#100000
b100 4
0.
03
0/
02
b1 5
1,
#200000
0,
#300000
b100 4
b100 5
1,
#400000
0,
#500000
1.
13
1,
#600000
0,
#700000
1,
#800000
0,
#900000
1,
#950000
b100 4
11
#1000000
b1 4
0,
00
#1100000
b10 4
b1 5
1,
#1200000
0,
#1300000
b10 4
0.
03
b10 5
1,
#1400000
0,
#1500000
1/
12
1,
#1600000
0,
#1700000
1,
#1800000
0,
#1900000
1,
#2000000
0,
#2100000
1,
#2200000
0,
#2300000
1,
#2400000
0,
#2500000
1,
#2600000
0,
#2700000
1,
#2800000
0,
#2900000
1,
#2950000
b1 4
01
#3000000
b1 4
0,
10
#3100000
b100 4
b1 5
1,
#3200000
0,
#3300000
b100 4
0/
02
b100 5
1,
